TextReplace-1.0.data/scripts/txt_replace
TextReplace-1.0.dist-info/DESCRIPTION.rst
TextReplace-1.0.dist-info/METADATA
TextReplace-1.0.dist-info/RECORD
TextReplace-1.0.dist-info/WHEEL
TextReplace-1.0.dist-info/metadata.json
TextReplace-1.0.dist-info/top_level.txt
txt_replace/__init__.py
txt_replace/main.py
