Metadata-Version: 2.0
Name: TextReplace
Version: 1.0
Summary: Replaces all matched strings                 in one directory with another
Home-page: https://github.com/LeafyLi/txtreplace
Author: zenglifa
Author-email: zenglifa@msu.edu
License: UNKNOWN
Platform: UNKNOWN
